conutils/__init__.py
conutils/_internals/__init__.py
conutils/_internals/console.py
conutils/_internals/entity/__init__.py
conutils/_internals/entity/entity.py
conutils/_internals/entity/container/__init__.py
conutils/_internals/entity/container/container.py
conutils/_internals/entity/elements/__init__.py
conutils/_internals/entity/elements/element.py
conutils/_internals/entity/elements/log.py
conutils/_internals/entity/elements/spinner.py
conutils/_internals/entity/elements/text.py
conutils/_internals/errors/__init__.py
conutils/_internals/errors/errorcodes.json
conutils/_internals/errors/errors.py
conutils/_internals/toolkit/__init__.py
conutils/_internals/toolkit/color.py
conutils/_internals/toolkit/compiler/__init__.py
conutils/_internals/toolkit/compiler/commons.py
conutils/_internals/toolkit/compiler/compiler_core.py
conutils/_internals/toolkit/compiler/multiproccesor.py
conutils-0.0.9.dist-info/METADATA
conutils-0.0.9.dist-info/WHEEL
conutils-0.0.9.dist-info/licenses/LICENSE
conutils-0.0.9.dist-info/RECORD
