Metadata-Version: 2.4
Name: ConUtils
Version: 0.0.9
Summary: a collection of console output fomating methods
Project-URL: Homepage, https://github.com/LePenner/ConUtils
Project-URL: Issues, https://github.com/LePenner/ConUtils/issues
Author-email: Kira <monoclecatstudio@gmail.com>
License-Expression: MIT
License-File: LICENSE
Classifier: Operating System :: OS Independent
Classifier: Programming Language :: Python :: 3
Requires-Python: >=3.12
